app_src/__init__.py
app_src/shiny_plots.py
app_src/shiny_server.py
app_src/shiny_user_interface.py
app_src/www/css/styles.css
app_src/www/img/analyse.svg
app_src/www/img/arrow_range.svg
app_src/www/img/chart.svg
app_src/www/img/download.svg
app_src/www/img/favicon.svg
app_src/www/img/gear.svg
app_src/www/img/logo.svg
app_src/www/img/number.svg
app_src/www/img/percent.svg
app_src/www/img/question.svg
app_src/www/img/ruler.svg
app_src/www/img/settings.svg
app_src/www/img/upload.svg
app_src/www/js/helper_functions.js
msaexplorer/__init__.py
msaexplorer/cli.py
msaexplorer/config.py
msaexplorer/draw.py
msaexplorer/explore.py
msaexplorer/export.py
msaexplorer-0.4.5.dist-info/licenses/LICENSE
msaexplorer-0.4.5.dist-info/METADATA
msaexplorer-0.4.5.dist-info/WHEEL
msaexplorer-0.4.5.dist-info/entry_points.txt
msaexplorer-0.4.5.dist-info/top_level.txt
msaexplorer-0.4.5.dist-info/RECORD
