Metadata-Version: 2.4
Name: msaexplorer
Version: 0.4.5
Summary: A tool for exploring multiple sequence alignments.
Author-email: Jonas Fuchs <jonas.fuchs@uniklinik-freiburg.de>
Maintainer-email: Jonas Fuchs <jonas.fuchs@uniklinik-freiburg.de>
License:                     GNU GENERAL PUBLIC LICENSE
Keywords: msa, multiple sequence alignments, plotting, shiny app, alignment analysis
Classifier: Programming Language :: Python :: 3.11
Classifier: Operating System :: OS Independent
Requires-Python: >=3.11
License-File: LICENSE
Requires-Dist: numpy>=2.0
Requires-Dist: matplotlib>=3.8
Provides-Extra: app
Requires-Dist: shinywidgets>=0.5.2; extra == "app"
Requires-Dist: shiny>=1.3; extra == "app"
Requires-Dist: plotly>=5.23; extra == "app"
Provides-Extra: app-plus
Requires-Dist: shinywidgets>=0.5.2; extra == "app-plus"
Requires-Dist: shiny>=1.3; extra == "app-plus"
Requires-Dist: plotly>=5.23; extra == "app-plus"
Requires-Dist: pyfamsa>=0.5.3; extra == "app-plus"
Requires-Dist: pytrimal>=0.8.1; extra == "app-plus"
Dynamic: license-file
